company_mcp/__init__.py
company_mcp/server.py
company_mcp/sse_server.py
company_mcp-0.1.0.dist-info/METADATA
company_mcp-0.1.0.dist-info/WHEEL
company_mcp-0.1.0.dist-info/entry_points.txt
company_mcp-0.1.0.dist-info/licenses/LICENSE
company_mcp-0.1.0.dist-info/RECORD
