Metadata-Version: 2.4
Name: company-mcp
Version: 0.1.0
Summary: MCP server for extracting AI companies and funding information from articles
Project-URL: Homepage, https://github.com/yourusername/company-mcp
Project-URL: Repository, https://github.com/yourusername/company-mcp
Author-email: Your Name <your@email.com>
License-Expression: MIT
License-File: LICENSE
Keywords: ai,company,extraction,funding,mcp
Classifier: Development Status :: 3 - Alpha
Classifier: Intended Audience :: Developers
Classifier: License :: OSI Approved :: MIT License
Classifier: Programming Language :: Python :: 3.12
Classifier: Programming Language :: Python :: 3.13
Requires-Python: >=3.12
Requires-Dist: beautifulsoup4>=4.12.0
Requires-Dist: httpx>=0.27.0
Requires-Dist: mcp[cli]>=1.0.0
Requires-Dist: openai>=1.0.0
Requires-Dist: python-dotenv>=1.0.0
Requires-Dist: starlette>=0.38.0
Requires-Dist: uvicorn>=0.30.0
